qtharmony/__init__.py
qtharmony/config/__init__.py
qtharmony/config/config.py
qtharmony/constructor/__init__.py
qtharmony/constructor/initialize.py
qtharmony/core/__init__.py
qtharmony/core/dialog.py
qtharmony/core/exceptions.py
qtharmony/core/font.py
qtharmony/core/load.py
qtharmony/core/sizes.py
qtharmony/core/stylesheet.py
qtharmony/core/theme/__init__.py
qtharmony/core/theme/theme_builder.py
qtharmony/core/theme/theme_manager.py
qtharmony/gui/icon.py
qtharmony/resources/__init__.py
qtharmony/resources/themes/dark-default.json
qtharmony/resources/themes/dark-green.json
qtharmony/resources/themes/light-default.json
qtharmony/resources/themes/light-green.json
qtharmony/resources/ui/Icon.png
qtharmony/resources/ui/Logo.png
qtharmony/resources/ui/angle-down.png
qtharmony/widgets/__init__.py
qtharmony/widgets/basic/button.py
qtharmony/widgets/basic/check_box.py
qtharmony/widgets/basic/digital_entry.py
qtharmony/widgets/basic/drop_down_menu.py
qtharmony/widgets/basic/entry.py
qtharmony/widgets/basic/frame.py
qtharmony/widgets/basic/groups.py
qtharmony/widgets/basic/label.py
qtharmony/widgets/basic/picture.py
qtharmony/widgets/basic/radio_button.py
qtharmony/widgets/basic/scrollbar.py
qtharmony/widgets/basic/splitter.py
qtharmony/widgets/basic/styles/button.css
qtharmony/widgets/basic/styles/check_box.css
qtharmony/widgets/basic/styles/digital_entry.css
qtharmony/widgets/basic/styles/drop_down_menu.css
qtharmony/widgets/basic/styles/entry.css
qtharmony/widgets/basic/styles/frame.css
qtharmony/widgets/basic/styles/group_box.css
qtharmony/widgets/basic/styles/label.css
qtharmony/widgets/basic/styles/path_entry.css
qtharmony/widgets/basic/styles/radio_button.css
qtharmony/widgets/basic/styles/scrollbar.css
qtharmony/widgets/basic/styles/splitter.css
qtharmony/widgets/basic/styles/text_box.css
qtharmony/widgets/basic/styles/widgets_list.css
qtharmony/widgets/basic/text_box.py
qtharmony/widgets/basic/widgets_list.py
qtharmony/widgets/custom/path_entry.py
qtharmony-0.3.4.dist-info/LICENSE
qtharmony-0.3.4.dist-info/METADATA
qtharmony-0.3.4.dist-info/WHEEL
qtharmony-0.3.4.dist-info/RECORD
