Metadata-Version: 2.1
Name: QtHarmony
Version: 0.3.4
Summary: 
License: MIT
Author: chebupelka8
Author-email: stpzamyatin@gmail.com
Requires-Python: >=3.11,<3.13
Classifier: License :: OSI Approved :: MIT License
Classifier: Programming Language :: Python :: 3
Classifier: Programming Language :: Python :: 3.11
Classifier: Programming Language :: Python :: 3.12
Requires-Dist: colorama (>=0.4.6,<0.5.0)
Requires-Dist: pyside6 (>=6.7.0,<7.0.0)
